CV_Tricks/__init__.py
CV_Tricks/img_frm_vid.py
CV_Tricks/img_to_vid.py
CV_Tricks-0.0.5.data/scripts/img_frm_vid.py
CV_Tricks-0.0.5.data/scripts/img_to_vid.py
CV_Tricks-0.0.5.dist-info/LICENSE
CV_Tricks-0.0.5.dist-info/METADATA
CV_Tricks-0.0.5.dist-info/WHEEL
CV_Tricks-0.0.5.dist-info/top_level.txt
CV_Tricks-0.0.5.dist-info/RECORD
