Metadata-Version: 2.1
Name: CV-Tricks
Version: 0.0.5
Summary: Tricks for Computer Vision Developers
Home-page: https://github.com/danial880/CV_Tricks
Author: Danial
Author-email: danialkhan1594@gmail.com
License: MIT
Keywords: ComputerVision
Platform: UNKNOWN
Classifier: Development Status :: 3 - Alpha
Classifier: Intended Audience :: Developers
Classifier: Intended Audience :: Education
Classifier: License :: OSI Approved :: MIT License
Classifier: Natural Language :: English
Classifier: Topic :: Scientific/Engineering
Classifier: Programming Language :: Python :: 3.7
Classifier: Programming Language :: Python :: 3.8
Classifier: Programming Language :: Python :: 3.9
Requires-Python: >=3.7
License-File: LICENSE
Requires-Dist: opencv-contrib-python
Requires-Dist: tqdm
Requires-Dist: setuptools
